dbabget/__init__.py
dbabget/dbabget.py
dbabget/douban_spider/__init__.py
dbabget/douban_spider/html_downloader.py
dbabget/douban_spider/html_outputer.py
dbabget/douban_spider/html_parser.py
dbabget/douban_spider/url_manger.py
dbabget-0.101.dist-info/METADATA
dbabget-0.101.dist-info/WHEEL
dbabget-0.101.dist-info/entry_points.txt
dbabget-0.101.dist-info/top_level.txt
dbabget-0.101.dist-info/RECORD
