Metadata-Version: 2.1
Name: dbabget
Version: 0.101
Summary: An awesome package that does something
Home-page: UNKNOWN
Author: huzi
License: MIT
Platform: UNKNOWN
Requires-Dist: beautifulsoup4 (>=4)
